py_dmenu/__init__.py
py_dmenu/dmenu.py
py_dmenu-0.1.1.dist-info/LICENSE
py_dmenu-0.1.1.dist-info/METADATA
py_dmenu-0.1.1.dist-info/WHEEL
py_dmenu-0.1.1.dist-info/top_level.txt
py_dmenu-0.1.1.dist-info/RECORD
